nlp_data/__init__.py
nlp_data/augment/__init__.py
nlp_data/augment/gpt.py
nlp_data/cli.py
nlp_data/document/__init__.py
nlp_data/document/api.py
nlp_data/document/dialogue.py
nlp_data/document/embedding.py
nlp_data/document/nlu.py
nlp_data/storage/__init__.py
nlp_data/storage/api.py
nlp_data/storage/base.py
nlp_data/storage/dialogue.py
nlp_data/storage/embdding.py
nlp_data/storage/nlu.py
nlp_data/storage/s3.py
nlp_data/utils.py
nlp_data-0.4.9.dist-info/METADATA
nlp_data-0.4.9.dist-info/WHEEL
nlp_data-0.4.9.dist-info/entry_points.txt
nlp_data-0.4.9.dist-info/RECORD
