Metadata-Version: 2.1
Name: nlp-data
Version: 0.4.9
Summary: 普强内部NLP数据存储分享处理工具
Author: gushuhua
Author-email: wangmengdi@pachiratech.com
Requires-Python: >=3.8,<4.0
Classifier: Programming Language :: Python :: 3
Classifier: Programming Language :: Python :: 3.8
Classifier: Programming Language :: Python :: 3.9
Classifier: Programming Language :: Python :: 3.10
Classifier: Programming Language :: Python :: 3.11
Classifier: Programming Language :: Python :: 3.12
Classifier: Programming Language :: Python :: 3.13
Requires-Dist: boto3 (>=1.28.8)
Requires-Dist: canto-filter (>=1.0.4)
Requires-Dist: docarray[aws,proto] (>=0.39)
Requires-Dist: jsonargparse (>=4.26.0,<5.0.0)
Requires-Dist: lightning-utilities (>=0.9.0,<0.10.0)
Requires-Dist: openai (>=1.3.7)
Requires-Dist: pydantic (>=1.10.8,<=1.10.15)
Requires-Dist: rich (>=13.4.2)
Requires-Dist: srsly (>=2.4.6)
Requires-Dist: tqdm (>=4.65.0)
Requires-Dist: wasabi (>=1.1.1)
